console_debugger/LICENSE
console_debugger/README.md
console_debugger/__init__.py
console_debugger/gui/__init__.py
console_debugger/gui/static/icons.ico
console_debugger/gui/tk_terminal.py
console_debugger/helpful/__init__.py
console_debugger/helpful/coloring_text.py
console_debugger/helpful/date_obj.py
console_debugger/helpful/template_obj.py
console_debugger/logic/__init__.py
console_debugger/logic/debugger.py
console_debugger/logic/mg_get_socket.py
console_debugger/logic/mg_send_socket.py
console_debugger/main.py
console_debugger/path_helper.py
console_debugger/requirements.txt
console_debugger/test/__init__.py
console_debugger/test/test_deb.py
console_debugger/test/test_socket.py
console_debugger/tui/__init__.py
console_debugger/tui/urw_widget.py
console_debugger/tui/urwid_terminal.py
console_debugger-0.1.8.8.dist-info/WHEEL
console_debugger-0.1.8.8.dist-info/METADATA
console_debugger-0.1.8.8.dist-info/RECORD
