Metadata-Version: 2.1
Name: console-debugger
Version: 0.1.8.8
Summary: Это подключаемая библиотека, для удобного вывода отладочной информации.
Home-page: https://github.com/denisxab/console_debugger
License: Apache-2.0
Keywords: debug,console,test,profiling,log,print
Author: Denis Kustov
Author-email: denis-kustov@rambler.ru
Requires-Python: >=3.5,<4.0
Classifier: License :: OSI Approved :: Apache Software License
Classifier: Programming Language :: Python :: 3
Classifier: Programming Language :: Python :: 3.5
Classifier: Programming Language :: Python :: 3.6
Classifier: Programming Language :: Python :: 3.7
Classifier: Programming Language :: Python :: 3.8
Classifier: Programming Language :: Python :: 3.9
Requires-Dist: urwid (>=2.1.2,<3.0.0)
Project-URL: Repository, https://github.com/denisxab/console_debugger
